{
  "openapi": "3.0.0",
  "info": {
    "title": "WebImpetus API V2",
    "version": "2.1"
  },
  "paths": {
    "/api/v2/businesses": {
      "get": {
        "tags": [
          "Businesses"
        ],
        "responses": {
          "200": {
            "description": "Get the businesses data"
          }
        },
        "security": [
          {
            "bearerAuth": []
          }
        ]
      },
      "post": {
        "tags": [
          "Businesses"
        ],
        "summary": "Create a new Business",
        "operationId": "createBusiness",
        "requestBody": {
          "required": true,
          "content": {
            "application/json": {
              "schema": {
                "$ref": "#/components/schemas/Businesses"
              }
            }
          }
        },
        "responses": {
          "200": {
            "description": "Created a business data"
          }
        },
        "security": [
          {
            "bearerAuth": []
          }
        ]
      }
    },
    "/api/v2/businesses/{uuid}": {
      "get": {
        "tags": [
          "Businesses"
        ],
        "parameters": [
          {
            "name": "uuid",
            "in": "path",
            "required": true,
            "description": "Unique identifier for the business",
            "schema": {
              "type": "string"
            }
          }
        ],
        "responses": {
          "200": {
            "description": "Get the single business data"
          }
        },
        "security": [
          {
            "bearerAuth": []
          }
        ]
      },
      "put": {
        "tags": [
          "Businesses"
        ],
        "parameters": [
          {
            "name": "uuid",
            "in": "path",
            "description": "The businesse uuid",
            "required": true,
            "schema": {
              "type": "string"
            }
          }
        ],
        "requestBody": {
          "required": true,
          "content": {
            "application/json": {
              "schema": {
                "$ref": "#/components/schemas/Businesses"
              }
            }
          }
        },
        "responses": {
          "200": {
            "description": "Updated a businesse data"
          }
        },
        "security": [
          {
            "bearerAuth": []
          }
        ]
      },
      "delete": {
        "tags": [
          "Businesses"
        ],
        "parameters": [
          {
            "name": "uuid",
            "in": "path",
            "description": "The businesse uuid",
            "required": true,
            "schema": {
              "type": "string"
            }
          }
        ],
        "responses": {
          "200": {
            "description": "Delete a businesse"
          }
        },
        "security": [
          {
            "bearerAuth": []
          }
        ]
      }
    },
    "/api/v2/addresses": {
      "get": {
        "tags": [
          "Addresses"
        ],
        "responses": {
          "200": {
            "description": "Get the addresses"
          }
        },
        "security": [
          {
            "bearerAuth": []
          }
        ]
      },
      "post": {
        "tags": [
          "Addresses"
        ],
        "summary": "Create a new Address",
        "operationId": "createAddress",
        "requestBody": {
          "required": true,
          "content": {
            "application/json": {
              "schema": {
                "$ref": "#/components/schemas/Addresses"
              }
            }
          }
        },
        "responses": {
          "200": {
            "description": "Created a Address data"
          }
        },
        "security": [
          {
            "bearerAuth": []
          }
        ]
      }
    },
    "/api/v2/addresses/{uuid}": {
      "get": {
        "tags": [
          "Addresses"
        ],
        "parameters": [
          {
            "name": "uuid",
            "in": "path",
            "description": "The addresses uuid",
            "required": true,
            "schema": {
              "type": "string"
            }
          }
        ],
        "responses": {
          "200": {
            "description": "Created a addresses data"
          }
        },
        "security": [
          {
            "bearerAuth": []
          }
        ]
      },
      "put": {
        "tags": [
          "Addresses"
        ],
        "parameters": [
          {
            "name": "uuid",
            "in": "path",
            "description": "The addresses uuid",
            "required": true,
            "schema": {
              "type": "string"
            }
          }
        ],
        "requestBody": {
          "required": true,
          "content": {
            "application/json": {
              "schema": {
                "$ref": "#/components/schemas/Addresses"
              }
            }
          }
        },
        "responses": {
          "200": {
            "description": "Updated a addresses data"
          }
        },
        "security": [
          {
            "bearerAuth": []
          }
        ]
      },
      "delete": {
        "tags": [
          "Addresses"
        ],
        "parameters": [
          {
            "name": "uuid",
            "in": "path",
            "description": "The addresses uuid",
            "required": true,
            "schema": {
              "type": "string"
            }
          }
        ],
        "responses": {
          "200": {
            "description": "Delete a addresses"
          }
        },
        "security": [
          {
            "bearerAuth": []
          }
        ]
      }
    },
    "/api/v2/companies": {
      "get": {
        "tags": [
          "Companies"
        ],
        "responses": {
          "200": {
            "description": "Get the companies"
          }
        },
        "security": [
          {
            "bearerAuth": []
          }
        ]
      },
      "post": {
        "tags": [
          "Companies"
        ],
        "summary": "Create a new Company",
        "operationId": "createCompany",
        "requestBody": {
          "required": true,
          "content": {
            "application/json": {
              "schema": {
                "$ref": "#/components/schemas/Companies"
              }
            }
          }
        },
        "responses": {
          "200": {
            "description": "Created a category data"
          }
        },
        "security": [
          {
            "bearerAuth": []
          }
        ]
      }
    },
    "/api/v2/companies/{uuid}": {
      "get": {
        "tags": [
          "Companies"
        ],
        "parameters": [
          {
            "name": "uuid",
            "in": "path",
            "description": "The companies uuid",
            "required": true,
            "schema": {
              "type": "string"
            }
          }
        ],
        "responses": {
          "200": {
            "description": "Created a companies data"
          }
        },
        "security": [
          {
            "bearerAuth": []
          }
        ]
      },
      "put": {
        "tags": [
          "Companies"
        ],
        "parameters": [
          {
            "name": "uuid",
            "in": "path",
            "description": "The companies uuid",
            "required": true,
            "schema": {
              "type": "string"
            }
          }
        ],
        "requestBody": {
          "required": true,
          "content": {
            "application/json": {
              "schema": {
                "$ref": "#/components/schemas/Companies"
              }
            }
          }
        },
        "responses": {
          "200": {
            "description": "Updated a companies data"
          }
        },
        "security": [
          {
            "bearerAuth": []
          }
        ]
      },
      "delete": {
        "tags": [
          "Companies"
        ],
        "parameters": [
          {
            "name": "uuid",
            "in": "path",
            "description": "The companies uuid",
            "required": true,
            "schema": {
              "type": "string"
            }
          }
        ],
        "responses": {
          "200": {
            "description": "Delete a companies"
          }
        },
        "security": [
          {
            "bearerAuth": []
          }
        ]
      }
    },
    "/api/v2/categories": {
      "get": {
        "tags": [
          "Categories"
        ],
        "responses": {
          "200": {
            "description": "Get the category data"
          }
        },
        "security": [
          {
            "bearerAuth": []
          }
        ]
      },
      "post": {
        "tags": [
          "Categories"
        ],
        "summary": "Create a new Categories",
        "operationId": "createCategory",
        "requestBody": {
          "required": true,
          "content": {
            "application/json": {
              "schema": {
                "$ref": "#/components/schemas/Categories"
              }
            }
          }
        },
        "responses": {
          "200": {
            "description": "Created a category data"
          }
        },
        "security": [
          {
            "bearerAuth": []
          }
        ]
      }
    },
    "/api/v2/categories/{uuid}": {
      "get": {
        "tags": [
          "Categories"
        ],
        "parameters": [
          {
            "name": "uuid",
            "in": "path",
            "description": "The category uuid",
            "required": true,
            "schema": {
              "type": "string"
            }
          }
        ],
        "responses": {
          "200": {
            "description": "Get the single category data"
          }
        },
        "security": [
          {
            "bearerAuth": []
          }
        ]
      },
      "put": {
        "tags": [
          "Categories"
        ],
        "parameters": [
          {
            "name": "uuid",
            "in": "path",
            "description": "The category uuid",
            "required": true,
            "schema": {
              "type": "string"
            }
          }
        ],
        "requestBody": {
          "required": true,
          "content": {
            "application/json": {
              "schema": {
                "$ref": "#/components/schemas/Categories"
              }
            }
          }
        },
        "responses": {
          "200": {
            "description": "Updated a category data"
          }
        },
        "security": [
          {
            "bearerAuth": []
          }
        ]
      },
      "delete": {
        "tags": [
          "Categories"
        ],
        "parameters": [
          {
            "name": "uuid",
            "in": "path",
            "description": "The category uuid",
            "required": true,
            "schema": {
              "type": "string"
            }
          }
        ],
        "responses": {
          "200": {
            "description": "Delete a category"
          }
        },
        "security": [
          {
            "bearerAuth": []
          }
        ]
      }
    },
    "/api/v2/contacts": {
      "get": {
        "tags": [
          "Contacts"
        ],
        "responses": {
          "200": {
            "description": "Get the contacts data"
          }
        },
        "security": [
          {
            "bearerAuth": []
          }
        ]
      },
      "post": {
        "tags": [
          "Contacts"
        ],
        "summary": "Create a new Contact",
        "operationId": "createContact",
        "requestBody": {
          "required": true,
          "content": {
            "application/json": {
              "schema": {
                "$ref": "#/components/schemas/Contacts"
              }
            }
          }
        },
        "responses": {
          "200": {
            "description": "Created a contact data"
          }
        },
        "security": [
          {
            "bearerAuth": []
          }
        ]
      }
    },
    "/api/v2/contacts/{uuid}": {
      "get": {
        "tags": [
          "Contacts"
        ],
        "parameters": [
          {
            "name": "uuid",
            "in": "path",
            "description": "The contact uuid",
            "required": true,
            "schema": {
              "type": "string"
            }
          }
        ],
        "responses": {
          "200": {
            "description": "Get the single contact data"
          }
        },
        "security": [
          {
            "bearerAuth": []
          }
        ]
      },
      "put": {
        "tags": [
          "Contacts"
        ],
        "parameters": [
          {
            "name": "uuid",
            "in": "path",
            "description": "The contact uuid",
            "required": true,
            "schema": {
              "type": "string"
            }
          }
        ],
        "requestBody": {
          "required": true,
          "content": {
            "application/json": {
              "schema": {
                "$ref": "#/components/schemas/Contacts"
              }
            }
          }
        },
        "responses": {
          "200": {
            "description": "Updated a contact data"
          }
        },
        "security": [
          {
            "bearerAuth": []
          }
        ]
      },
      "delete": {
        "tags": [
          "Contacts"
        ],
        "parameters": [
          {
            "name": "uuid",
            "in": "path",
            "description": "The contact uuid",
            "required": true,
            "schema": {
              "type": "string"
            }
          }
        ],
        "responses": {
          "200": {
            "description": "Delete a contact"
          }
        },
        "security": [
          {
            "bearerAuth": []
          }
        ]
      }
    },
    "/api/v2/customers": {
      "get": {
        "tags": [
          "Customers"
        ],
        "responses": {
          "200": {
            "description": "Get the Customers data"
          }
        },
        "security": [
          {
            "bearerAuth": []
          }
        ]
      },
      "post": {
        "tags": [
          "Customers"
        ],
        "summary": "Create a new Customer",
        "operationId": "createCustomer",
        "requestBody": {
          "required": true,
          "content": {
            "application/json": {
              "schema": {
                "$ref": "#/components/schemas/Customers"
              }
            }
          }
        },
        "responses": {
          "200": {
            "description": "Created a customer data"
          }
        },
        "security": [
          {
            "bearerAuth": []
          }
        ]
      }
    },
    "/api/v2/customers/{uuid}": {
      "get": {
        "tags": [
          "Customers"
        ],
        "parameters": [
          {
            "name": "uuid",
            "in": "path",
            "description": "The customer uuid",
            "required": true,
            "schema": {
              "type": "string"
            }
          }
        ],
        "responses": {
          "200": {
            "description": "Get the single customer data"
          }
        },
        "security": [
          {
            "bearerAuth": []
          }
        ]
      },
      "put": {
        "tags": [
          "Customers"
        ],
        "parameters": [
          {
            "name": "uuid",
            "in": "path",
            "description": "The customer uuid",
            "required": true,
            "schema": {
              "type": "string"
            }
          }
        ],
        "requestBody": {
          "required": true,
          "content": {
            "application/json": {
              "schema": {
                "$ref": "#/components/schemas/Customers"
              }
            }
          }
        },
        "responses": {
          "200": {
            "description": "Updated a customer data"
          }
        },
        "security": [
          {
            "bearerAuth": []
          }
        ]
      },
      "delete": {
        "tags": [
          "Customers"
        ],
        "parameters": [
          {
            "name": "uuid",
            "in": "path",
            "description": "The customer uuid",
            "required": true,
            "schema": {
              "type": "string"
            }
          }
        ],
        "responses": {
          "200": {
            "description": "Delete a customer"
          }
        },
        "security": [
          {
            "bearerAuth": []
          }
        ]
      }
    },
    "/api/v2/vm": {
      "get": {
        "tags": [
          "Virtual Machines"
        ],
        "responses": {
          "200": {
            "description": "Get the Virtual Machines"
          }
        },
        "security": [
          {
            "bearerAuth": []
          }
        ]
      },
      "post": {
        "tags": [
          "Virtual Machines"
        ],
        "summary": "Create a new Virtual Machines",
        "operationId": "createVM",
        "requestBody": {
          "required": true,
          "content": {
            "application/json": {
              "schema": {
                "$ref": "#/components/schemas/VM"
              }
            }
          }
        },
        "responses": {
          "200": {
            "description": "Created a category data"
          }
        },
        "security": [
          {
            "bearerAuth": []
          }
        ]
      }
    },
    "/api/v2/vm/{uuid}": {
      "get": {
        "tags": [
          "Virtual Machines"
        ],
        "parameters": [
          {
            "name": "uuid",
            "in": "path",
            "description": "The Virtual Machines uuid",
            "required": true,
            "schema": {
              "type": "string"
            }
          }
        ],
        "responses": {
          "200": {
            "description": "Created a Virtual Machines data"
          }
        },
        "security": [
          {
            "bearerAuth": []
          }
        ]
      },
      "put": {
        "tags": [
          "Virtual Machines"
        ],
        "parameters": [
          {
            "name": "uuid",
            "in": "path",
            "description": "The Virtual Machines uuid",
            "required": true,
            "schema": {
              "type": "string"
            }
          }
        ],
        "requestBody": {
          "required": true,
          "content": {
            "application/json": {
              "schema": {
                "$ref": "#/components/schemas/VM"
              }
            }
          }
        },
        "responses": {
          "200": {
            "description": "Updated a companies data"
          }
        },
        "security": [
          {
            "bearerAuth": []
          }
        ]
      },
      "delete": {
        "tags": [
          "Companies"
        ],
        "parameters": [
          {
            "name": "uuid",
            "in": "path",
            "description": "The companies uuid",
            "required": true,
            "schema": {
              "type": "string"
            }
          }
        ],
        "responses": {
          "200": {
            "description": "Delete a companies"
          }
        },
        "security": [
          {
            "bearerAuth": []
          }
        ]
      }
    },
    "/api/v2/employees": {
      "get": {
        "tags": [
          "Employee"
        ],
        "responses": {
          "200": {
            "description": "Get the employees data"
          }
        },
        "security": [
          {
            "bearerAuth": []
          }
        ]
      },
      "post": {
        "tags": [
          "Employee"
        ],
        "summary": "Create a new Employee",
        "operationId": "createEmployee",
        "requestBody": {
          "required": true,
          "content": {
            "application/json": {
              "schema": {
                "$ref": "#/components/schemas/Contacts"
              }
            }
          }
        },
        "responses": {
          "200": {
            "description": "Created a employee data"
          }
        },
        "security": [
          {
            "bearerAuth": []
          }
        ]
      }
    },
    "/api/v2/employees/{uuid}": {
      "get": {
        "tags": [
          "Employee"
        ],
        "parameters": [
          {
            "name": "uuid",
            "in": "path",
            "description": "The employee uuid",
            "required": true,
            "schema": {
              "type": "string"
            }
          }
        ],
        "responses": {
          "200": {
            "description": "Get the single Employee data"
          }
        },
        "security": [
          {
            "bearerAuth": []
          }
        ]
      },
      "put": {
        "tags": [
          "Employee"
        ],
        "parameters": [
          {
            "name": "uuid",
            "in": "path",
            "description": "The employee uuid",
            "required": true,
            "schema": {
              "type": "string"
            }
          }
        ],
        "requestBody": {
          "required": true,
          "content": {
            "application/json": {
              "schema": {
                "$ref": "#/components/schemas/Contacts"
              }
            }
          }
        },
        "responses": {
          "200": {
            "description": "Updated a employee data"
          }
        },
        "security": [
          {
            "bearerAuth": []
          }
        ]
      },
      "delete": {
        "tags": [
          "Employee"
        ],
        "parameters": [
          {
            "name": "uuid",
            "in": "path",
            "description": "The employee uuid",
            "required": true,
            "schema": {
              "type": "string"
            }
          }
        ],
        "responses": {
          "200": {
            "description": "Delete a employee"
          }
        },
        "security": [
          {
            "bearerAuth": []
          }
        ]
      }
    },
    "/api/v2/menu": {
      "get": {
        "tags": [
          "Menu"
        ],
        "responses": {
          "200": {
            "description": "Get the menues data"
          }
        },
        "security": [
          {
            "bearerAuth": []
          }
        ]
      },
      "post": {
        "tags": [
          "Menu"
        ],
        "summary": "Create a new Menu",
        "operationId": "createMenu",
        "requestBody": {
          "required": true,
          "content": {
            "application/json": {
              "schema": {
                "$ref": "#/components/schemas/Menu"
              }
            }
          }
        },
        "responses": {
          "200": {
            "description": "Created a menu data"
          }
        },
        "security": [
          {
            "bearerAuth": []
          }
        ]
      }
    },
    "/api/v2/menu/{uuid}": {
      "get": {
        "tags": [
          "Menu"
        ],
        "parameters": [
          {
            "name": "uuid",
            "in": "path",
            "description": "The menu uuid",
            "required": true,
            "schema": {
              "type": "string"
            }
          }
        ],
        "responses": {
          "200": {
            "description": "Get the single menu data"
          }
        },
        "security": [
          {
            "bearerAuth": []
          }
        ]
      },
      "put": {
        "tags": [
          "Menu"
        ],
        "parameters": [
          {
            "name": "uuid",
            "in": "path",
            "description": "The menu uuid",
            "required": true,
            "schema": {
              "type": "string"
            }
          }
        ],
        "requestBody": {
          "required": true,
          "content": {
            "application/json": {
              "schema": {
                "$ref": "#/components/schemas/Menu"
              }
            }
          }
        },
        "responses": {
          "200": {
            "description": "Updated a menu data"
          }
        },
        "security": [
          {
            "bearerAuth": []
          }
        ]
      },
      "delete": {
        "tags": [
          "Menu"
        ],
        "parameters": [
          {
            "name": "uuid",
            "in": "path",
            "description": "The menu uuid",
            "required": true,
            "schema": {
              "type": "string"
            }
          }
        ],
        "responses": {
          "200": {
            "description": "Delete a menu"
          }
        },
        "security": [
          {
            "bearerAuth": []
          }
        ]
      }
    },
    "/api/v2/products": {
      "get": {
        "tags": [
          "Products"
        ],
        "responses": {
          "200": {
            "description": "Get the menues data"
          }
        },
        "security": [
          {
            "bearerAuth": []
          }
        ]
      },
      "post": {
        "tags": [
          "Products"
        ],
        "summary": "Create a new Products",
        "operationId": "createProducts",
        "requestBody": {
          "required": true,
          "content": {
            "application/json": {
              "schema": {
                "$ref": "#/components/schemas/Products"
              }
            }
          }
        },
        "responses": {
          "200": {
            "description": "Created a menu data"
          }
        },
        "security": [
          {
            "bearerAuth": []
          }
        ]
      }
    },
    "/api/v2/products/{uuid}": {
      "get": {
        "tags": [
          "Products"
        ],
        "parameters": [
          {
            "name": "uuid",
            "in": "path",
            "description": "The products uuid",
            "required": true,
            "schema": {
              "type": "string"
            }
          }
        ],
        "responses": {
          "200": {
            "description": "Get the single menu data"
          }
        },
        "security": [
          {
            "bearerAuth": []
          }
        ]
      },
      "put": {
        "tags": [
          "Products"
        ],
        "parameters": [
          {
            "name": "uuid",
            "in": "path",
            "description": "The menu uuid",
            "required": true,
            "schema": {
              "type": "string"
            }
          }
        ],
        "requestBody": {
          "required": true,
          "content": {
            "application/json": {
              "schema": {
                "$ref": "#/components/schemas/Products"
              }
            }
          }
        },
        "responses": {
          "200": {
            "description": "Updated a menu data"
          }
        },
        "security": [
          {
            "bearerAuth": []
          }
        ]
      },
      "delete": {
        "tags": [
          "Products"
        ],
        "parameters": [
          {
            "name": "uuid",
            "in": "path",
            "description": "The menu uuid",
            "required": true,
            "schema": {
              "type": "string"
            }
          }
        ],
        "responses": {
          "200": {
            "description": "Delete a menu"
          }
        },
        "security": [
          {
            "bearerAuth": []
          }
        ]
      }
    },
    "/api/v2/projects": {
      "get": {
        "tags": [
          "Projects"
        ],
        "responses": {
          "200": {
            "description": "Get the projects data"
          }
        },
        "security": [
          {
            "bearerAuth": []
          }
        ]
      },
      "post": {
        "tags": [
          "Projects"
        ],
        "summary": "Create a new Projects",
        "operationId": "createProjects",
        "requestBody": {
          "required": true,
          "content": {
            "application/json": {
              "schema": {
                "$ref": "#/components/schemas/Projects"
              }
            }
          }
        },
        "responses": {
          "200": {
            "description": "Created a sprint data"
          }
        },
        "security": [
          {
            "bearerAuth": []
          }
        ]
      }
    },
    "/api/v2/projects/{uuid}": {
      "get": {
        "tags": [
          "Projects"
        ],
        "parameters": [
          {
            "name": "uuid",
            "in": "path",
            "description": "The project uuid",
            "required": true,
            "schema": {
              "type": "string"
            }
          }
        ],
        "responses": {
          "200": {
            "description": "Get the single project data"
          }
        },
        "security": [
          {
            "bearerAuth": []
          }
        ]
      },
      "put": {
        "tags": [
          "Projects"
        ],
        "parameters": [
          {
            "name": "uuid",
            "in": "path",
            "description": "The project uuid",
            "required": true,
            "schema": {
              "type": "string"
            }
          }
        ],
        "requestBody": {
          "required": true,
          "content": {
            "application/json": {
              "schema": {
                "$ref": "#/components/schemas/Projects"
              }
            }
          }
        },
        "responses": {
          "200": {
            "description": "Updated a project data"
          }
        },
        "security": [
          {
            "bearerAuth": []
          }
        ]
      },
      "delete": {
        "tags": [
          "Projects"
        ],
        "parameters": [
          {
            "name": "uuid",
            "in": "path",
            "description": "The project uuid",
            "required": true,
            "schema": {
              "type": "string"
            }
          }
        ],
        "responses": {
          "200": {
            "description": "Delete a project"
          }
        },
        "security": [
          {
            "bearerAuth": []
          }
        ]
      }
    },
    "/api/v2/sprints": {
      "get": {
        "tags": [
          "Sprints"
        ],
        "responses": {
          "200": {
            "description": "Get the sprints data"
          }
        },
        "security": [
          {
            "bearerAuth": []
          }
        ]
      },
      "post": {
        "tags": [
          "Sprints"
        ],
        "summary": "Create a new Sprints",
        "operationId": "createSprints",
        "requestBody": {
          "required": true,
          "content": {
            "application/json": {
              "schema": {
                "$ref": "#/components/schemas/Sprints"
              }
            }
          }
        },
        "responses": {
          "200": {
            "description": "Created a sprint data"
          }
        },
        "security": [
          {
            "bearerAuth": []
          }
        ]
      }
    },
    "/api/v2/sprints/{uuid}": {
      "get": {
        "tags": [
          "Sprints"
        ],
        "parameters": [
          {
            "name": "uuid",
            "in": "path",
            "description": "The sprint uuid",
            "required": true,
            "schema": {
              "type": "string"
            }
          }
        ],
        "responses": {
          "200": {
            "description": "Get the single sprint data"
          }
        },
        "security": [
          {
            "bearerAuth": []
          }
        ]
      },
      "put": {
        "tags": [
          "Sprints"
        ],
        "parameters": [
          {
            "name": "uuid",
            "in": "path",
            "description": "The sprint uuid",
            "required": true,
            "schema": {
              "type": "string"
            }
          }
        ],
        "requestBody": {
          "required": true,
          "content": {
            "application/json": {
              "schema": {
                "$ref": "#/components/schemas/Sprints"
              }
            }
          }
        },
        "responses": {
          "200": {
            "description": "Updated a sprint data"
          }
        },
        "security": [
          {
            "bearerAuth": []
          }
        ]
      },
      "delete": {
        "tags": [
          "Sprints"
        ],
        "parameters": [
          {
            "name": "uuid",
            "in": "path",
            "description": "The sprint uuid",
            "required": true,
            "schema": {
              "type": "string"
            }
          }
        ],
        "responses": {
          "200": {
            "description": "Delete a sprint"
          }
        },
        "security": [
          {
            "bearerAuth": []
          }
        ]
      }
    },
    "/api/v2/tasks": {
      "get": {
        "tags": [
          "Tasks"
        ],
        "responses": {
          "200": {
            "description": "Get the tasks data"
          }
        },
        "security": [
          {
            "bearerAuth": []
          }
        ]
      },
      "post": {
        "tags": [
          "Tasks"
        ],
        "summary": "Create a new Tasks",
        "operationId": "createTasks",
        "requestBody": {
          "required": true,
          "content": {
            "application/json": {
              "schema": {
                "$ref": "#/components/schemas/Tasks"
              }
            }
          }
        },
        "responses": {
          "200": {
            "description": "Created a task"
          }
        },
        "security": [
          {
            "bearerAuth": []
          }
        ]
      }
    },
    "/api/v2/tasks/{uuid}": {
      "get": {
        "tags": [
          "Tasks"
        ],
        "parameters": [
          {
            "name": "uuid",
            "in": "path",
            "description": "The task uuid",
            "required": true,
            "schema": {
              "type": "string"
            }
          }
        ],
        "responses": {
          "200": {
            "description": "Get the single task data"
          }
        },
        "security": [
          {
            "bearerAuth": []
          }
        ]
      },
      "put": {
        "tags": [
          "Tasks"
        ],
        "parameters": [
          {
            "name": "uuid",
            "in": "path",
            "description": "The task uuid",
            "required": true,
            "schema": {
              "type": "string"
            }
          }
        ],
        "requestBody": {
          "required": true,
          "content": {
            "application/json": {
              "schema": {
                "$ref": "#/components/schemas/Tasks"
              }
            }
          }
        },
        "responses": {
          "200": {
            "description": "Updated a task data"
          }
        },
        "security": [
          {
            "bearerAuth": []
          }
        ]
      },
      "delete": {
        "tags": [
          "Tasks"
        ],
        "parameters": [
          {
            "name": "uuid",
            "in": "path",
            "description": "The task uuid",
            "required": true,
            "schema": {
              "type": "string"
            }
          }
        ],
        "responses": {
          "200": {
            "description": "Delete a task"
          }
        },
        "security": [
          {
            "bearerAuth": []
          }
        ]
      }
    },
    "/api/v2/timeslips": {
      "get": {
        "tags": [
          "Timeslips"
        ],
        "responses": {
          "200": {
            "description": "Get the timeslips data"
          }
        },
        "security": [
          {
            "bearerAuth": []
          }
        ]
      },
      "post": {
        "tags": [
          "Timeslips"
        ],
        "summary": "Create a new Timeslips",
        "operationId": "createTimeslips",
        "requestBody": {
          "required": true,
          "content": {
            "application/json": {
              "schema": {
                "$ref": "#/components/schemas/Timeslips"
              }
            }
          }
        },
        "responses": {
          "200": {
            "description": "Created a timeslip"
          }
        },
        "security": [
          {
            "bearerAuth": []
          }
        ]
      }
    },
    "/api/v2/timeslips/{uuid}": {
      "get": {
        "tags": [
          "Timeslips"
        ],
        "parameters": [
          {
            "name": "uuid",
            "in": "path",
            "description": "The timeslip uuid",
            "required": true,
            "schema": {
              "type": "string"
            }
          }
        ],
        "responses": {
          "200": {
            "description": "Get the single timeslip data"
          }
        },
        "security": [
          {
            "bearerAuth": []
          }
        ]
      },
      "put": {
        "tags": [
          "Timeslips"
        ],
        "parameters": [
          {
            "name": "uuid",
            "in": "path",
            "description": "The timeslip uuid",
            "required": true,
            "schema": {
              "type": "string"
            }
          }
        ],
        "requestBody": {
          "required": true,
          "content": {
            "application/json": {
              "schema": {
                "$ref": "#/components/schemas/Timeslips"
              }
            }
          }
        },
        "responses": {
          "200": {
            "description": "Updated a timeslip data"
          }
        },
        "security": [
          {
            "bearerAuth": []
          }
        ]
      },
      "delete": {
        "tags": [
          "Timeslips"
        ],
        "parameters": [
          {
            "name": "uuid",
            "in": "path",
            "description": "The timeslip uuid",
            "required": true,
            "schema": {
              "type": "string"
            }
          }
        ],
        "responses": {
          "200": {
            "description": "Delete a timeslip"
          }
        },
        "security": [
          {
            "bearerAuth": []
          }
        ]
      }
    },
    "/api/v2/users": {
      "get": {
        "tags": [
          "User"
        ],
        "responses": {
          "200": {
            "description": "Get the users data"
          }
        },
        "security": [
          {
            "bearerAuth": []
          }
        ]
      },
      "post": {
        "tags": [
          "User"
        ],
        "summary": "Create a new User",
        "operationId": "createUser",
        "requestBody": {
          "required": true,
          "content": {
            "application/json": {
              "schema": {
                "$ref": "#/components/schemas/Users"
              }
            }
          }
        },
        "responses": {
          "200": {
            "description": "Updated a user data"
          }
        },
        "security": [
          {
            "bearerAuth": []
          }
        ]
      }
    },
    "/api/v2/users/{uuid}": {
      "get": {
        "tags": [
          "User"
        ],
        "parameters": [
          {
            "name": "uuid",
            "in": "path",
            "description": "The user uuid",
            "required": true,
            "schema": {
              "type": "string"
            }
          }
        ],
        "responses": {
          "200": {
            "description": "Get the single user data"
          }
        },
        "security": [
          {
            "bearerAuth": []
          }
        ]
      },
      "put": {
        "tags": [
          "User"
        ],
        "parameters": [
          {
            "name": "uuid",
            "in": "path",
            "description": "The user uuid",
            "required": true,
            "schema": {
              "type": "string"
            }
          }
        ],
        "requestBody": {
          "required": true,
          "content": {
            "application/json": {
              "schema": {
                "$ref": "#/components/schemas/Users"
              }
            }
          }
        },
        "responses": {
          "200": {
            "description": "Updated a user data"
          }
        },
        "security": [
          {
            "bearerAuth": []
          }
        ]
      },
      "delete": {
        "tags": [
          "User"
        ],
        "parameters": [
          {
            "name": "uuid",
            "in": "path",
            "description": "The user uuid",
            "required": true,
            "schema": {
              "type": "string"
            }
          }
        ],
        "responses": {
          "200": {
            "description": "Delete a user"
          }
        },
        "security": [
          {
            "bearerAuth": []
          }
        ]
      }
    },
    "/api/v2/webpages": {
      "get": {
        "tags": [
          "Webpage"
        ],
        "responses": {
          "200": {
            "description": "Get the webpages data"
          }
        },
        "security": [
          {
            "bearerAuth": []
          }
        ]
      },
      "post": {
        "tags": [
          "Webpage"
        ],
        "summary": "Create a new Webpage",
        "operationId": "createWebpage",
        "requestBody": {
          "required": true,
          "content": {
            "application/json": {
              "schema": {
                "$ref": "#/components/schemas/Webpage"
              }
            }
          }
        },
        "responses": {
          "200": {
            "description": "Updated a webpage data"
          }
        },
        "security": [
          {
            "bearerAuth": []
          }
        ]
      }
    },
    "/api/v2/webpages/{uuid}": {
      "get": {
        "tags": [
          "Webpage"
        ],
        "parameters": [
          {
            "name": "uuid",
            "in": "path",
            "description": "The webpage uuid",
            "required": true,
            "schema": {
              "type": "string"
            }
          }
        ],
        "responses": {
          "200": {
            "description": "Get the single webpage data"
          }
        },
        "security": [
          {
            "bearerAuth": []
          }
        ]
      },
      "put": {
        "tags": [
          "Webpage"
        ],
        "parameters": [
          {
            "name": "uuid",
            "in": "path",
            "description": "The webpage uuid",
            "required": true,
            "schema": {
              "type": "string"
            }
          }
        ],
        "requestBody": {
          "required": true,
          "content": {
            "application/json": {
              "schema": {
                "$ref": "#/components/schemas/Webpage"
              }
            }
          }
        },
        "responses": {
          "200": {
            "description": "Updated a webpage data"
          }
        },
        "security": [
          {
            "bearerAuth": []
          }
        ]
      },
      "delete": {
        "tags": [
          "Webpage"
        ],
        "parameters": [
          {
            "name": "uuid",
            "in": "path",
            "description": "The webpage uuid",
            "required": true,
            "schema": {
              "type": "string"
            }
          }
        ],
        "responses": {
          "200": {
            "description": "Delete a webpage"
          }
        },
        "security": [
          {
            "bearerAuth": []
          }
        ]
      }
    }
  },
  "components": {
    "securitySchemes": {
      "bearerAuth": {
        "type": "http",
        "bearerFormat": "JWT",
        "scheme": "bearer"
      }
    },
    "schemas": {
      "Businesses": {
        "type": "object",
        "properties": {
          "email": {
            "type": "string",
            "default": "mail@email.com"
          },
          "company_address": {
            "type": "string",
            "default": "test"
          },
          "company_number": {
            "type": "number",
            "default": 9876543210
          },
          "vat_number": {
            "type": "string",
            "default": "BAC123"
          },
          "no_of_shares": {
            "type": "string",
            "default": "test"
          },
          "web_site": {
            "type": "string",
            "default": "https://google.com"
          },
          "payment_page_url": {
            "type": "string",
            "default": "https://payment.com"
          },
          "country_code": {
            "type": "string",
            "default": "IN"
          },
          "telephone_no": {
            "type": "number",
            "default": 9876543318
          },
          "trading_as": {
            "type": "string",
            "default": "test"
          },
          "business_contacts": {
            "type": "string",
            "default": "test"
          },
          "default_business": {
            "type": "string",
            "default": "test"
          },
          "uuid_business_id": {
            "type": "string",
            "default": "test"
          }
        }
      },
      "Addresses": {
        "type": "object",
        "properties": {
          "address_line_1": {
            "type": "string",
            "default": "Address line 1"
          },
          "address_line_2": {
            "type": "string",
            "default": "Address line 2"
          },
          "address_line_3": {
            "type": "string",
            "default": "Address line 3"
          },
          "address_line_4": {
            "type": "string",
            "default": "Address line 4"
          },
          "city": {
            "type": "string",
            "default": "City"
          },
          "state": {
            "type": "string",
            "default": "State"
          },
          "country": {
            "type": "string",
            "default": "Country"
          },
          "post_code": {
            "type": "string",
            "default": "Post code"
          },
          "uuid_contact": {
            "type": "string",
            "default": "uuid contact"
          },
          "uuid_user": {
            "type": "string",
            "default": "uuid user"
          },
          "uuid_customer": {
            "type": "string",
            "default": "uuid customer"
          },
          "address_type": {
            "type": "string",
            "default": "address type"
          },
          "uuid_business_id": {
            "type": "string",
            "default": "test"
          }
        }
      },
      "Companies": {
        "type": "object",
        "properties": {
          "company_number": {
            "type": "number",
            "default": 8765432
          },
          "company_name": {
            "type": "string",
            "default": "test"
          },
          "address_1": {
            "type": "string",
            "default": "test"
          },
          "address_2": {
            "type": "string",
            "default": "test"
          },
          "address_3": {
            "type": "string",
            "default": "test"
          },
          "town_or_city": {
            "type": "string",
            "default": "test"
          },
          "state_or_county": {
            "type": "string",
            "default": "test"
          },
          "post_zip_code": {
            "type": "number",
            "default": 12345
          },
          "region_area": {
            "type": "string",
            "default": "test"
          },
          "website": {
            "type": "string",
            "default": "https://test.com"
          },
          "email": {
            "type": "string",
            "default": "mail@email.com"
          },
          "premises_type": {
            "type": "string",
            "default": "test"
          },
          "no_of_employees": {
            "type": "number",
            "default": 33
          },
          "company_type": {
            "type": "string",
            "default": "test"
          },
          "sic_code": {
            "type": "number",
            "default": 223432
          },
          "turnover": {
            "type": "number",
            "default": "1,23,444"
          },
          "company_telephone": {
            "type": "number",
            "default": 333344445555
          },
          "company_fax": {
            "type": "number",
            "default": 332233444
          },
          "contactID": {
            "type": "string",
            "default": "UUID of contact"
          },
          "uuid_business": {
            "type": "string",
            "default": "UUID of business"
          }
        }
      },
      "Categories": {
        "type": "object",
        "properties": {
          "user_uuid": {
            "type": "string",
            "default": "UUID of User"
          },
          "name": {
            "type": "string",
            "default": "test"
          },
          "notes": {
            "type": "string",
            "default": "test"
          },
          "image_logo": {
            "type": "string",
            "default": "long blob"
          },
          "uuid_business_id": {
            "type": "string",
            "default": "UUID of business"
          },
          "sort_order": {
            "type": "number",
            "default": 1
          },
          "contact_uuid": {
            "type": "string",
            "default": "UUID of contacts"
          }
        }
      },
      "Contacts": {
        "type": "object",
        "properties": {
          "linked_module_types": {
            "type": "string",
            "default": "customers or companies"
          },
          "customer_id": {
            "type": "string",
            "default": "id of customer if customers selected"
          },
          "company_id": {
            "type": "string",
            "default": "id of company if companies selected"
          },
          "first_name": {
            "type": "string",
            "default": "test"
          },
          "surname": {
            "type": "string",
            "default": "test"
          },
          "title": {
            "type": "string",
            "default": "test"
          },
          "saludation": {
            "type": "string",
            "default": "test"
          },
          "comments": {
            "type": "string",
            "default": "test"
          },
          "news_letter_status": {
            "type": "string",
            "default": "test"
          },
          "allow_web_access": {
            "type": "number",
            "default": "0/1"
          },
          "email": {
            "type": "string",
            "default": "test@mail.com"
          },
          "password": {
            "type": "string",
            "default": "test"
          },
          "direct_phone": {
            "type": "number",
            "default": 22333444555
          },
          "mobile": {
            "type": "number",
            "default": 33333222221
          },
          "direct_fax": {
            "type": "string",
            "default": "test"
          },
          "uuid_business_id": {
            "type": "string",
            "default": "UUID of business"
          },
          "contact_type": {
            "type": "string",
            "default": "test"
          }
        }
      },
      "Customers": {
        "type": "object",
        "properties": {
          "company_name": {
            "type": "string",
            "default": "company name"
          },
          "acc_no": {
            "type": "string",
            "default": "test"
          },
          "status": {
            "type": "number",
            "default": "0/1"
          },
          "contact_firstname": {
            "type": "string",
            "default": "test"
          },
          "contact_lastname": {
            "type": "string",
            "default": "test"
          },
          "email": {
            "type": "string",
            "default": "test@mail.com"
          },
          "address1": {
            "type": "string",
            "default": "test"
          },
          "address2": {
            "type": "number",
            "default": "0/1"
          },
          "city": {
            "type": "string",
            "default": "test"
          },
          "country": {
            "type": "string",
            "default": "test"
          },
          "postal_code": {
            "type": "number",
            "default": 22333444555
          },
          "phone": {
            "type": "number",
            "default": 33333222221
          },
          "notes": {
            "type": "string",
            "default": "test"
          },
          "supplier": {
            "type": "number",
            "default": "0/1"
          },
          "website": {
            "type": "string",
            "default": "https://website.com"
          },
          "uuid_business_id": {
            "type": "string",
            "default": "UUID of business"
          },
          "categories": {
            "type": "string",
            "default": "ids of categories [\"14\", \"8\"]"
          }
        }
      },
      "VM": {
        "type": "object",
        "properties": {
          "vm_name": {
            "type": "string",
            "default": "Name of VM"
          },
          "vm_code": {
            "type": "string",
            "default": "Unique code of VM"
          },
          "vm_cpu_cores": {
            "type": "string",
            "default": "VM CPU Cores"
          },
          "vm_ram_display": {
            "type": "string",
            "default": "VM Ram"
          },
          "vm_ipv4": {
            "type": "string",
            "default": "VM IPv4"
          },
          "vm_ipv6": {
            "type": "string",
            "default": "VM IPv6"
          },
          "vm_tags": {
            "type": "array",
            "items": {}
          },
          "vm_categories": {
            "type": "array",
            "items": {}
          },
          "vm_description": {
            "type": "string",
            "default": "description"
          },
          "status": {
            "type": "number",
            "default": "0/1"
          },
          "uuid_business_id": {
            "type": "string",
            "default": "UUID of business"
          }
        }
      },
      "Menu": {
        "type": "object",
        "properties": {
          "name": {
            "type": "string",
            "default": "menu name"
          },
          "link": {
            "type": "string",
            "default": "link of menu"
          },
          "icon": {
            "type": "string",
            "default": "icon of menu"
          },
          "sort_order": {
            "type": "number",
            "default": 22
          },
          "language_code": {
            "type": "string",
            "default": "en"
          },
          "menu_fts": {
            "type": "string",
            "default": "test"
          },
          "uuid_business_id": {
            "type": "string",
            "default": "UUID of business"
          }
        }
      },
      "Products": {
        "type": "object",
        "properties": {
          "product_name": {
            "type": "string",
            "default": "product name"
          },
          "product_code": {
            "type": "string",
            "default": "product code"
          },
          "product_description": {
            "type": "string",
            "default": "product description"
          },
          "product_category": {
            "type": "string",
            "default": "product category"
          },
          "product_sku": {
            "type": "string",
            "default": "product sku"
          },
          "is_published": {
            "type": "number",
            "default": "0/1"
          },
          "unit_price": {
            "type": "number",
            "default": 12.34
          },
          "sort_order": {
            "type": "number",
            "default": 34
          },
          "uuid_business_id": {
            "type": "string",
            "default": "UUID of business"
          }
        }
      },
      "Projects": {
        "type": "object",
        "properties": {
          "customers_id": {
            "type": "string",
            "default": "id of customer"
          },
          "name": {
            "type": "string",
            "default": "name of project"
          },
          "start_date": {
            "type": "string",
            "default": "start date"
          },
          "budget": {
            "type": "string",
            "default": "project budget"
          },
          "rate": {
            "type": "string",
            "default": "project rate"
          },
          "currency": {
            "type": "number",
            "default": "USD"
          },
          "deadline_date": {
            "type": "string",
            "default": "deadline date"
          },
          "employees_id": {
            "type": "number",
            "default": "id of employee"
          },
          "active": {
            "type": "number",
            "default": "0/1"
          },
          "uuid_business_id": {
            "type": "string",
            "default": "UUID of business"
          }
        }
      },
      "Sprints": {
        "type": "object",
        "properties": {
          "sprint_name": {
            "type": "string",
            "default": "sprint name"
          },
          "start_date": {
            "type": "string",
            "default": "start date"
          },
          "end_date": {
            "type": "string",
            "default": "end date"
          },
          "note": {
            "type": "string",
            "default": "note"
          },
          "uuid_business_id": {
            "type": "string",
            "default": "UUID of business"
          }
        }
      },
      "Tasks": {
        "type": "object",
        "properties": {
          "name": {
            "type": "string",
            "default": "task name"
          },
          "reported_by": {
            "type": "string",
            "default": "reported employee id"
          },
          "projects_id": {
            "type": "string",
            "default": "projects id"
          },
          "start_date": {
            "type": "number",
            "default": "start date"
          },
          "end_date": {
            "type": "number",
            "default": "end date"
          },
          "estimated_hour": {
            "type": "number",
            "default": "estimated hour"
          },
          "rate": {
            "type": "number",
            "default": 23.4
          },
          "status": {
            "type": "string",
            "default": "status"
          },
          "active": {
            "type": "number",
            "default": "0/1"
          },
          "assigned_to": {
            "type": "number",
            "default": "id of employee"
          },
          "task_id": {
            "type": "number",
            "default": "task id"
          },
          "customers_id": {
            "type": "number",
            "default": "customers id"
          },
          "contacts_id": {
            "type": "number",
            "default": "contacts id"
          },
          "description": {
            "type": "string",
            "default": "description"
          },
          "file": {
            "type": "string",
            "default": "long blob"
          },
          "category": {
            "type": "string",
            "default": "category id"
          },
          "priority": {
            "type": "string",
            "default": "priority"
          },
          "sprint_id": {
            "type": "number",
            "default": "sprint id"
          },
          "uuid_business_id": {
            "type": "string",
            "default": "UUID of business"
          }
        }
      },
      "Timeslips": {
        "type": "object",
        "properties": {
          "task_name": {
            "type": "string",
            "default": "task name"
          },
          "week_no": {
            "type": "string",
            "default": "week no"
          },
          "employee_name": {
            "type": "string",
            "default": "employee id"
          },
          "slip_start_date": {
            "type": "number",
            "default": "slip start date"
          },
          "slip_timer_started": {
            "type": "number",
            "default": "slip start time"
          },
          "slip_end_date": {
            "type": "number",
            "default": "slip end date"
          },
          "slip_timer_end": {
            "type": "number",
            "default": "slip end time"
          },
          "break_time": {
            "type": "number",
            "default": "break time in hour"
          },
          "break_time_start": {
            "type": "number",
            "default": "break time start"
          },
          "break_time_end": {
            "type": "string",
            "default": "break time end"
          },
          "slip_hours": {
            "type": "number",
            "default": 1.5
          },
          "slip_description": {
            "type": "string",
            "default": "slip description"
          },
          "slip_rate": {
            "type": "number",
            "default": "slip rate"
          },
          "slip_timer_accumulated_seconds": {
            "type": "number",
            "default": "slip timer accumulated seconds"
          },
          "billing_status": {
            "type": "string",
            "default": "billing status"
          },
          "uuid_business_id": {
            "type": "string",
            "default": "UUID of business"
          }
        }
      },
      "Users": {
        "type": "object",
        "properties": {
          "name": {
            "type": "string",
            "default": "user name"
          },
          "email": {
            "type": "string",
            "default": "user email"
          },
          "password": {
            "type": "string",
            "default": "user password"
          },
          "address": {
            "type": "string",
            "default": "user address"
          },
          "status": {
            "type": "number",
            "default": "0/1"
          },
          "role": {
            "type": "string",
            "default": "user role uuid"
          },
          "notes": {
            "type": "string",
            "default": "notes"
          },
          "date_time": {
            "type": "number",
            "default": "date time"
          },
          "permissions": {
            "type": "string",
            "default": "permissions menu ids"
          },
          "language_code": {
            "type": "string",
            "default": "en"
          },
          "token": {
            "type": "string",
            "default": "user token"
          },
          "profile_img": {
            "type": "string",
            "default": "long blob"
          },
          "uuid_business_id": {
            "type": "string",
            "default": "UUID of business"
          }
        }
      },
      "Webpage": {
        "type": "object",
        "properties": {
          "title": {
            "type": "string",
            "default": "title of page"
          },
          "sub_title": {
            "type": "string",
            "default": "sub title of page"
          },
          "content": {
            "type": "string",
            "default": "content of page"
          },
          "type": {
            "type": "number",
            "default": "0/1"
          },
          "status": {
            "type": "number",
            "default": "0/1"
          },
          "code": {
            "type": "string",
            "default": "code for the page block"
          },
          "meta_title": {
            "type": "string",
            "default": "meta title"
          },
          "meta_description": {
            "type": "number",
            "default": "meta description"
          },
          "meta_keywords": {
            "type": "string",
            "default": "meta keywords"
          },
          "custom_fields": {
            "type": "string",
            "default": "custom fields uuid"
          },
          "custom_assets": {
            "type": "string",
            "default": "custom assets"
          },
          "user_uuid": {
            "type": "string",
            "default": "user uuid"
          },
          "publish_date": {
            "type": "number",
            "default": "timestamp"
          },
          "categories": {
            "type": "string",
            "default": "categories ids"
          },
          "published_date": {
            "type": "string",
            "default": "date of publish"
          },
          "language_code": {
            "type": "string",
            "default": "en"
          },
          "blog_type": {
            "type": "string",
            "default": "0/1 (0 = private, 1 = public)"
          },
          "uuid_business_id": {
            "type": "string",
            "default": "UUID of business"
          }
        }
      }
    }
  }
}